erk_statusline/__init__.py
erk_statusline/__main__.py
erk_statusline/colored_tokens.py
erk_statusline/context.py
erk_statusline/py.typed
erk_statusline/statusline.py
erk_statusline-0.7.0.dist-info/METADATA
erk_statusline-0.7.0.dist-info/WHEEL
erk_statusline-0.7.0.dist-info/entry_points.txt
erk_statusline-0.7.0.dist-info/RECORD
