Metadata-Version: 2.4
Name: erk-statusline
Version: 0.7.0
Summary: Custom status line for Claude Code with robbyrussell theme style
Requires-Python: >=3.11
Requires-Dist: erk-shared
